{
  "version": "5",
  "dialect": "pg",
  "entries": [
    {
      "idx": 0,
      "version": "5",
      "when": 1683746502918,
      "tag": "0000_lying_purple_man",
      "breakpoints": false
    },
    {
      "idx": 1,
      "version": "5",
      "when": 1683862065530,
      "tag": "0001_charming_true_believers",
      "breakpoints": false
    },
    {
      "idx": 2,
      "version": "5",
      "when": 1683863512362,
      "tag": "0002_bent_absorbing_man",
      "breakpoints": false
    },
    {
      "idx": 3,
      "version": "5",
      "when": 1683920598362,
      "tag": "0003_military_preak",
      "breakpoints": false
    },
    {
      "idx": 4,
      "version": "5",
      "when": 1684101179715,
      "tag": "0004_numerous_yellow_claw",
      "breakpoints": false
    },
    {
      "idx": 5,
      "version": "5",
      "when": 1684106948837,
      "tag": "0005_thin_jasper_sitwell",
      "breakpoints": false
    },
    {
      "idx": 6,
      "version": "5",
      "when": 1684129572637,
      "tag": "0006_chilly_scream",
      "breakpoints": false
    },
    {
      "idx": 7,
      "version": "5",
      "when": 1684201534679,
      "tag": "0007_overjoyed_azazel",
      "breakpoints": false
    },
    {
      "idx": 8,
      "version": "5",
      "when": 1684202184084,
      "tag": "0008_black_tenebrous",
      "breakpoints": false
    },
    {
      "idx": 9,
      "version": "5",
      "when": 1684207371142,
      "tag": "0009_plain_scarlet_spider",
      "breakpoints": false
    },
    {
      "idx": 10,
      "version": "5",
      "when": 1684211138640,
      "tag": "0010_faithful_maestro",
      "breakpoints": false
    },
    {
      "idx": 11,
      "version": "5",
      "when": 1684219924765,
      "tag": "0011_absurd_iron_patriot",
      "breakpoints": false
    },
    {
      "idx": 12,
      "version": "5",
      "when": 1684267854082,
      "tag": "0012_past_darwin",
      "breakpoints": false
    },
    {
      "idx": 13,
      "version": "5",
      "when": 1684298442673,
      "tag": "0013_quiet_genesis",
      "breakpoints": false
    },
    {
      "idx": 14,
      "version": "5",
      "when": 1684337194944,
      "tag": "0014_pink_white_tiger",
      "breakpoints": false
    },
    {
      "idx": 15,
      "version": "5",
      "when": 1684534477328,
      "tag": "0015_cheerful_smasher",
      "breakpoints": false
    },
    {
      "idx": 16,
      "version": "5",
      "when": 1684612776482,
      "tag": "0016_cute_lyja",
      "breakpoints": false
    },
    {
      "idx": 17,
      "version": "5",
      "when": 1684619488823,
      "tag": "0017_nappy_captain_stacy",
      "breakpoints": false
    },
    {
      "idx": 18,
      "version": "5",
      "when": 1684625241433,
      "tag": "0018_swift_amazoness",
      "breakpoints": false
    },
    {
      "idx": 19,
      "version": "5",
      "when": 1684773803115,
      "tag": "0019_lucky_wild_child",
      "breakpoints": false
    },
    {
      "idx": 20,
      "version": "5",
      "when": 1684872883926,
      "tag": "0020_handy_inhumans",
      "breakpoints": false
    },
    {
      "idx": 21,
      "version": "5",
      "when": 1684947618684,
      "tag": "0021_lush_redwing",
      "breakpoints": false
    },
    {
      "idx": 22,
      "version": "5",
      "when": 1684957188358,
      "tag": "0022_curved_flatman",
      "breakpoints": false
    },
    {
      "idx": 23,
      "version": "5",
      "when": 1684959550411,
      "tag": "0023_stiff_tiger_shark",
      "breakpoints": false
    },
    {
      "idx": 24,
      "version": "5",
      "when": 1684969757333,
      "tag": "0024_noisy_lester",
      "breakpoints": false
    },
    {
      "idx": 25,
      "version": "5",
      "when": 1684969921781,
      "tag": "0025_wandering_titanium_man",
      "breakpoints": false
    },
    {
      "idx": 26,
      "version": "5",
      "when": 1684976309638,
      "tag": "0026_condemned_skaar",
      "breakpoints": false
    },
    {
      "idx": 27,
      "version": "5",
      "when": 1684981782082,
      "tag": "0027_flawless_baron_zemo",
      "breakpoints": false
    },
    {
      "idx": 28,
      "version": "5",
      "when": 1685202223644,
      "tag": "0028_deep_piledriver",
      "breakpoints": false
    },
    {
      "idx": 29,
      "version": "5",
      "when": 1685237736227,
      "tag": "0029_cloudy_tony_stark",
      "breakpoints": false
    },
    {
      "idx": 30,
      "version": "5",
      "when": 1685238080230,
      "tag": "0030_whole_captain_universe",
      "breakpoints": false
    },
    {
      "idx": 31,
      "version": "5",
      "when": 1686597438510,
      "tag": "0031_grey_avengers",
      "breakpoints": false
    },
    {
      "idx": 32,
      "version": "5",
      "when": 1686616279074,
      "tag": "0032_outstanding_cobalt_man",
      "breakpoints": false
    },
    {
      "idx": 33,
      "version": "5",
      "when": 1686618557905,
      "tag": "0033_nasty_callisto",
      "breakpoints": false
    },
    {
      "idx": 34,
      "version": "5",
      "when": 1686620557352,
      "tag": "0034_round_prodigy",
      "breakpoints": false
    },
    {
      "idx": 35,
      "version": "5",
      "when": 1686857162539,
      "tag": "0035_aspiring_richard_fisk",
      "breakpoints": false
    },
    {
      "idx": 36,
      "version": "5",
      "when": 1686861231574,
      "tag": "0036_flippant_starjammers",
      "breakpoints": false
    },
    {
      "idx": 37,
      "version": "5",
      "when": 1686862013560,
      "tag": "0037_common_silhouette",
      "breakpoints": false
    },
    {
      "idx": 38,
      "version": "5",
      "when": 1686937710427,
      "tag": "0038_shiny_george_stacy",
      "breakpoints": false
    },
    {
      "idx": 39,
      "version": "5",
      "when": 1686940689689,
      "tag": "0039_wild_invaders",
      "breakpoints": false
    },
    {
      "idx": 40,
      "version": "5",
      "when": 1686970367136,
      "tag": "0040_tired_sharon_carter",
      "breakpoints": false
    },
    {
      "idx": 41,
      "version": "5",
      "when": 1686985271015,
      "tag": "0041_thin_domino",
      "breakpoints": false
    },
    {
      "idx": 42,
      "version": "5",
      "when": 1687036018243,
      "tag": "0042_chemical_starbolt",
      "breakpoints": false
    },
    {
      "idx": 43,
      "version": "5",
      "when": 1687066887184,
      "tag": "0043_grey_jamie_braddock",
      "breakpoints": false
    },
    {
      "idx": 44,
      "version": "5",
      "when": 1687073851096,
      "tag": "0044_stale_silk_fever",
      "breakpoints": false
    },
    {
      "idx": 45,
      "version": "5",
      "when": 1687715016751,
      "tag": "0045_bitter_starjammers",
      "breakpoints": false
    },
    {
      "idx": 46,
      "version": "5",
      "when": 1688060754516,
      "tag": "0046_wet_toro",
      "breakpoints": false
    },
    {
      "idx": 47,
      "version": "5",
      "when": 1694172234610,
      "tag": "0047_narrow_retro_girl",
      "breakpoints": false
    },
    {
      "idx": 48,
      "version": "5",
      "when": 1694422012121,
      "tag": "0048_naive_ulik",
      "breakpoints": false
    },
    {
      "idx": 49,
      "version": "5",
      "when": 1694442062506,
      "tag": "0049_early_killer_shrike",
      "breakpoints": false
    },
    {
      "idx": 50,
      "version": "5",
      "when": 1694445385464,
      "tag": "0050_wakeful_rachel_grey",
      "breakpoints": false
    },
    {
      "idx": 51,
      "version": "5",
      "when": 1694509658221,
      "tag": "0051_hard_spencer_smythe",
      "breakpoints": false
    },
    {
      "idx": 52,
      "version": "5",
      "when": 1694612169557,
      "tag": "0052_jittery_turbo",
      "breakpoints": false
    },
    {
      "idx": 53,
      "version": "5",
      "when": 1696381243533,
      "tag": "0053_unknown_vulture",
      "breakpoints": false
    },
    {
      "idx": 54,
      "version": "5",
      "when": 1696381743762,
      "tag": "0054_icy_mentor",
      "breakpoints": false
    },
    {
      "idx": 55,
      "version": "5",
      "when": 1696456079853,
      "tag": "0055_sleepy_susan_delgado",
      "breakpoints": false
    },
    {
      "idx": 56,
      "version": "5",
      "when": 1696470816531,
      "tag": "0056_orange_sally_floyd",
      "breakpoints": false
    },
    {
      "idx": 57,
      "version": "5",
      "when": 1696476442289,
      "tag": "0057_smiling_the_santerians",
      "breakpoints": false
    },
    {
      "idx": 58,
      "version": "5",
      "when": 1697249122134,
      "tag": "0058_slimy_dracula",
      "breakpoints": false
    },
    {
      "idx": 59,
      "version": "5",
      "when": 1697304544091,
      "tag": "0059_living_wiccan",
      "breakpoints": false
    },
    {
      "idx": 60,
      "version": "5",
      "when": 1697332096842,
      "tag": "0060_woozy_screwball",
      "breakpoints": false
    },
    {
      "idx": 61,
      "version": "5",
      "when": 1699209841415,
      "tag": "0061_sturdy_quasimodo",
      "breakpoints": false
    }
  ]
}